pankmer-0.20.1.dist-info/METADATA
pankmer-0.20.1.dist-info/WHEEL
pankmer-0.20.1.dist-info/entry_points.txt
pankmer/parse_genomes_input.py
pankmer/tree.py
pankmer/collect.py
pankmer/version.py
pankmer/env.py
pankmer/clustermap.py
pankmer/anchor.py
pankmer/download.py
pankmer/datasets.py
pankmer/__init__.py
pankmer/adjacency_matrix.py
pankmer/upset.py
pankmer/subset.py
pankmer/view.py
pankmer/gzip_agnostic_open.py
pankmer/anchormap.py
pankmer/count.py
pankmer/dryrun.py
pankmer/pankmer.py
pankmer/index.cpython-310-darwin.so
pankmer-0.20.1.dist-info/RECORD
