Metadata-Version: 2.3
Name: pankmer
Version: 0.20.1
Classifier: Programming Language :: Rust
Classifier: Programming Language :: Python :: 3
Classifier: Programming Language :: Python :: Implementation :: CPython
Classifier: Programming Language :: Python :: Implementation :: PyPy
Classifier: Operating System :: OS Independent
Classifier: License :: OSI Approved :: BSD License
Requires-Dist: biopython
Requires-Dist: gff2bed
Requires-Dist: newick
Requires-Dist: pyfaidx
Requires-Dist: scipy
Requires-Dist: seaborn
Requires-Dist: urllib3
Requires-Dist: upsetplot
Requires-Dist: pybedtools
Requires-Dist: more-itertools
Requires-Dist: dash-bootstrap-components
Summary: Generate a PanGenome given a set of genomes
Author: Semar Petrus
Author-email: Anthony Aylward <anthony.aylward@protonmail.com>, Allen Mamerto <amamerto@salk.edu>, Nolan Hartwick <nhartwick@salk.edu>
Requires-Python: >=3.10
Project-URL: Homepage, https://gitlab.com/salk-tm/pankmer
Project-URL: Documentation, https://salk-tm.gitlab.io/pankmer
